LICENSE.txt
MANIFEST.in
README.md
setup.py
BlackLager.egg-info/PKG-INFO
BlackLager.egg-info/SOURCES.txt
BlackLager.egg-info/dependency_links.txt
BlackLager.egg-info/entry_points.txt
BlackLager.egg-info/requires.txt
BlackLager.egg-info/top_level.txt
blackLager/__init__.py
blackLager/__main__.py
blackLager/admin_pb2.py
blackLager/apponly_pb2.py
blackLager/black_lager_app.py
blackLager/ble.py
blackLager/ble_interface.py
blackLager/cannedmessages_pb2.py
blackLager/channel_pb2.py
blackLager/client_utils.py
blackLager/config_pb2.py
blackLager/crypto_utils.py
blackLager/device_metadata_pb2.py
blackLager/deviceonly_pb2.py
blackLager/globals.py
blackLager/localonly_pb2.py
blackLager/mesh_interface.py
blackLager/mesh_pb2.py
blackLager/module_config_pb2.py
blackLager/mqtt_pb2.py
blackLager/node.py
blackLager/persona_pb2.py
blackLager/persona_wallet.py
blackLager/portnums_pb2.py
blackLager/remote_hardware.py
blackLager/remote_hardware_pb2.py
blackLager/serial_interface.py
blackLager/storeforward_pb2.py
blackLager/stream_interface.py
blackLager/supported_device.py
blackLager/tcp_interface.py
blackLager/telemetry_pb2.py
blackLager/test.py
blackLager/textpad.py
blackLager/textwindow.py
blackLager/tunnel.py
blackLager/util.py